quotely/__init__.py
quotely/core.py
quotely/py.typed
quotely-1.0.0.dist-info/licenses/LICENSE
quotely-1.0.0.dist-info/METADATA
quotely-1.0.0.dist-info/WHEEL
quotely-1.0.0.dist-info/top_level.txt
quotely-1.0.0.dist-info/RECORD
